rpg/__init__.py
rpg/driver.py
randompw_generator-1.0.2.dist-info/LICENSE
randompw_generator-1.0.2.dist-info/METADATA
randompw_generator-1.0.2.dist-info/WHEEL
randompw_generator-1.0.2.dist-info/top_level.txt
randompw_generator-1.0.2.dist-info/RECORD
