Metadata-Version: 2.1
Name: randompw-generator
Version: 1.0.2
Summary: Random password generator
Home-page: https://github.com/saurzv/randompw-generator
Author: Saurav Raj
Author-email: <saurav.raj5592@gmail.com>
License: MIT
Keywords: python,random,password,generator,random password generator
Platform: UNKNOWN
Classifier: License :: OSI Approved :: MIT License
Classifier: Development Status :: 1 - Planning
Classifier: Intended Audience :: Developers
Classifier: Programming Language :: Python :: 3.6
Classifier: Programming Language :: Python :: 3.7
Classifier: Programming Language :: Python :: 3.8
Classifier: Operating System :: Unix
Classifier: Operating System :: MacOS :: MacOS X
Classifier: Operating System :: Microsoft :: Windows
